LICENSE
README.md
pyproject.toml
setup.cfg
setup.py
chatblade/__init__.py
chatblade/__main__.py
chatblade/chat.py
chatblade/cli.py
chatblade/errors.py
chatblade/parser.py
chatblade/printer.py
chatblade/session.py
chatblade/storage.py
chatblade/utils.py
chatblade.egg-info/PKG-INFO
chatblade.egg-info/SOURCES.txt
chatblade.egg-info/dependency_links.txt
chatblade.egg-info/entry_points.txt
chatblade.egg-info/requires.txt
chatblade.egg-info/top_level.txt