Metadata-Version: 2.1
Name: chatblade
Version: 0.5.0
Summary: CLI Swiss Army Knife for ChatGPT
Home-page: https://github.com/npiv/chatblade
Project-URL: Documentation, https://github.com/npiv/chatblade
Keywords: chatblade chatgpt cli python
License-File: LICENSE
Requires-Dist: openai~=1.35.15
Requires-Dist: tiktoken~=0.7.0
Requires-Dist: rich~=13.7.1
Requires-Dist: PyYAML~=6.0.1
Requires-Dist: platformdirs~=4.2.2
